qolimpervious/__init__.py
qolimpervious/qolimpervious.py
qolimpervious-1.5.dist-info/LICENSE.txt
qolimpervious-1.5.dist-info/METADATA
qolimpervious-1.5.dist-info/WHEEL
qolimpervious-1.5.dist-info/top_level.txt
qolimpervious-1.5.dist-info/RECORD
