Metadata-Version: 2.1
Name: qolimpervious
Version: 1.5
Summary: This library executes impervious surface analysis for the Quality of Life Exporer dashboard
Home-page: https://github.com/ProvidenceAdu/qolimpervious
Author: Providence Adu,Ph.D.
Author-email: <padu@charlotte.edu>
Keywords: urban institute,python,Mecklenburg County,quality of life explorer,impervious,NPA
License-File: LICENSE.txt
Requires-Dist: pandas >=1.0.0
